pydrobert/__init__.py
pydrobert/torch/__init__.py
pydrobert/torch/command_line.py
pydrobert/torch/data.py
pydrobert/torch/estimators.py
pydrobert/torch/layers.py
pydrobert/torch/training.py
pydrobert/torch/util.py
pydrobert/torch/version.py
pydrobert_pytorch-0.3.0.dist-info/LICENSE
pydrobert_pytorch-0.3.0.dist-info/METADATA
pydrobert_pytorch-0.3.0.dist-info/WHEEL
pydrobert_pytorch-0.3.0.dist-info/entry_points.txt
pydrobert_pytorch-0.3.0.dist-info/top_level.txt
pydrobert_pytorch-0.3.0.dist-info/RECORD
