Metadata-Version: 2.1
Name: pydrobert-pytorch
Version: 0.3.0
Summary: "PyTorch utilities for ML, specifically speech"
Home-page: https://github.com/sdrobert/pydrobert-pytorch
Author: Sean Robertson
Author-email: sdrobert@cs.toronto.edu
License: Apache-2.0
Project-URL: Documentation, https://pydrobert-pytorch.readthedocs.io
Platform: UNKNOWN
Classifier: Development Status :: 3 - Alpha
Classifier: License :: OSI Approved :: Apache Software License
Classifier: Programming Language :: Python :: 3
Requires-Python: >=3.6
Requires-Dist: numpy
Requires-Dist: torch (>=1.0.1)
Requires-Dist: param
